doxypypyplantuml/__init__.py
doxypypyplantuml/doxypypyplantuml.py
doxypypyplantuml-1.0.0.dist-info/entry_points.txt
doxypypyplantuml-1.0.0.dist-info/LICENSE
doxypypyplantuml-1.0.0.dist-info/WHEEL
doxypypyplantuml-1.0.0.dist-info/METADATA
doxypypyplantuml-1.0.0.dist-info/RECORD
