Metadata-Version: 2.1
Name: doxypypyplantuml
Version: 1.0.0
Summary: A package that fixes PlantUML diagrams that doxypypy screws up.
Keywords: doxypypy,Doxygen,PlantUML
Author-email: Stef van Son <8822160+stefvanson@users.noreply.github.com>
Requires-Python: >=3.6
Classifier: Development Status :: 5 - Production/Stable
Classifier: Environment :: Console
Classifier: Intended Audience :: Developers
Classifier: License :: OSI Approved :: MIT License
Classifier: Natural Language :: English
Classifier: Operating System :: OS Independent
Classifier: Programming Language :: Python :: 3
Classifier: Topic :: Software Development :: Documentation
Project-URL: Bug Tracker, https://github.com/stefvanson/doxypypyplantuml/issues
Project-URL: Homepage, https://github.com/stefvanson/doxypypyplantuml
